grammar_graph/__init__.py
grammar_graph/gg.py
grammar_graph/helpers.py
grammar_graph/type_defs.py
grammar_graph-0.2.0.dist-info/LICENSE
grammar_graph-0.2.0.dist-info/METADATA
grammar_graph-0.2.0.dist-info/WHEEL
grammar_graph-0.2.0.dist-info/top_level.txt
grammar_graph-0.2.0.dist-info/RECORD
