Metadata-Version: 2.1
Name: grammar_graph
Version: 0.2.0
Summary: Graphs from Context-Free Grammars.
Author-email: Dominic Steinhoefel <dominic.steinhoefel@cispa.de>
License: GNU GENERAL PUBLIC LICENSE
Project-URL: Homepage, https://github.com/rindPHI/GrammarGraph/
Project-URL: Bug Tracker, https://github.com/rindPHI/GrammarGraph/issues
Classifier: Intended Audience :: Science/Research
Classifier: License :: OSI Approved :: GNU General Public License v3 (GPLv3)
Classifier: Programming Language :: Python :: 3
Classifier: Operating System :: OS Independent
Classifier: Topic :: Scientific/Engineering
Requires-Python: >=3.10
License-File: LICENSE
Requires-Dist: fibheap >=0.2.1
Requires-Dist: graphviz >=0.20
Requires-Dist: wheel >=0.37.1
Provides-Extra: dev
Requires-Dist: black >=22.8.0 ; extra == 'dev'
Requires-Dist: build >=0.8.0 ; extra == 'dev'
Provides-Extra: test
Requires-Dist: fuzzingbook >=1.1 ; extra == 'test'
Requires-Dist: pytest-pycharm >=0.7.0 ; extra == 'test'
Requires-Dist: pytest-xdist ==2.5.0 ; extra == 'test'
Requires-Dist: pytest >=6.2.5 ; extra == 'test'
